<?xml version="1.0" encoding="windows-1252" ?>
<!DOCTYPE ViewLink SYSTEM "jbo_03_01.dtd">
<!---->
<ViewLink
  xmlns="http://xmlns.oracle.com/bc4j"
  Name="ZRptSalesDataZRptSaFk1Link"
  Version="12.2.1.20.47"
  InheritPersonalization="merge"
  EntityAssociation="model.ZRptSalesDataZRptSaFk1Assoc">
  <ViewLinkDefEnd
    Name="Z_Rpt_Sales_ParamView"
    Cardinality="1"
    Source="true"
    Owner="model.Z_Rpt_Sales_ParamView">
    <DesignTime>
      <Attr Name="_isUpdateable" Value="true"/>
      <Attr Name="_finderName" Value="Z_Rpt_Sales_ParamView"/>
    </DesignTime>
    <AttrArray Name="Attributes">
      <Item Value="model.Z_Rpt_Sales_ParamView.ZRptSalesParamId"/>
    </AttrArray>
  </ViewLinkDefEnd>
  <ViewLinkDefEnd
    Name="Z_Rpt_Sales_DataView"
    Cardinality="-1"
    Owner="model.Z_Rpt_Sales_DataView">
    <DesignTime>
      <Attr Name="_isUpdateable" Value="true"/>
      <Attr Name="_finderName" Value="Z_Rpt_Sales_DataView"/>
    </DesignTime>
    <AttrArray Name="Attributes">
      <Item Value="model.Z_Rpt_Sales_DataView.ZRptSalesParamIdFk"/>
    </AttrArray>
  </ViewLinkDefEnd>
</ViewLink>
